{
    "cmwelsh": {
        "openness": 0.8531598739222997,
        "conscientiousness": 0.6367918174727762,
        "extraversion": 0.6003810106531224,
        "agreeableness": 0.649741009605872,
        "neuroticism": 0.583041092130344
    },
    "christianalfoni": {
        "openness": 0.829969136894967,
        "conscientiousness": 0.6370212625916974,
        "extraversion": 0.4855586271191584,
        "agreeableness": 0.6794480436599679,
        "neuroticism": 0.5153565378569226
    },
    "srconklin": {
        "openness": 0.825900229140778,
        "conscientiousness": 0.6116025772288948,
        "extraversion": 0.469262990520967,
        "agreeableness": 0.6273927663418175,
        "neuroticism": 0.535930456877525
    },
    "FoxxMD": {
        "openness": 0.8199487054846017,
        "conscientiousness": 0.6054376792680994,
        "extraversion": 0.46952313265830614,
        "agreeableness": 0.6426563730707131,
        "neuroticism": 0.5076354245164129
    },
    "aesopwolf": {
        "openness": 0.7952220350250697,
        "conscientiousness": 0.6029479501963919,
        "extraversion": 0.4572266061785999,
        "agreeableness": 0.6522528978455571,
        "neuroticism": 0.4971129744708967
    },
    "BrettThePark": {
        "openness": 0.8405734943069062,
        "conscientiousness": 0.6295324165770495,
        "extraversion": 0.5216525219599303,
        "agreeableness": 0.6590826902363891,
        "neuroticism": 0.541886322418243
    },
    "gilbarbara": {
        "openness": 0.7872680363543754,
        "conscientiousness": 0.613578955856281,
        "extraversion": 0.4582327996107124,
        "agreeableness": 0.6730127193682054,
        "neuroticism": 0.5228124335642306
    },
    "sdemjanenko": {
        "openness": 0.8384533355289374,
        "conscientiousness": 0.601691797069242,
        "extraversion": 0.4676715971464543,
        "agreeableness": 0.6384875021717418,
        "neuroticism": 0.4990430076992861
    },
    "eriklharper": {
        "openness": 0.8120727852445293,
        "conscientiousness": 0.6058922659306871,
        "extraversion": 0.49908251208725446,
        "agreeableness": 0.6219157591165768,
        "neuroticism": 0.5375589170322548
    },
    "tnrich": {
        "openness": 0.8231663974225978,
        "conscientiousness": 0.5885354605519444,
        "extraversion": 0.49220565352771756,
        "agreeableness": 0.6955536778349924,
        "neuroticism": 0.5047704980969897
    },
    "mull": {
        "openness": 0.8056891252367414,
        "conscientiousness": 0.5728150548257931,
        "extraversion": 0.41259666865194466,
        "agreeableness": 0.6170464796288073,
        "neuroticism": 0.4947144891141711
    },
    "kristian-puccio": {
        "openness": 0.8202262064705594,
        "conscientiousness": 0.5655435244549245,
        "extraversion": 0.48883878744494863,
        "agreeableness": 0.6083737111229355,
        "neuroticism": 0.4966291454516817
    },
    "rojobuffalo": {
        "openness": 0.8734565811782056,
        "conscientiousness": 0.5898534386424951,
        "extraversion": 0.5461479038703145,
        "agreeableness": 0.6432362237671427,
        "neuroticism": 0.5168652574779837
    },
    "frost555": {
        "openness": 0.8143358552604953,
        "conscientiousness": 0.5814638625554175,
        "extraversion": 0.5325391405134472,
        "agreeableness": 0.6731344904116257,
        "neuroticism": 0.5390768669692934
    },
    "philippotto": {
        "openness": 0.8400195235866469,
        "conscientiousness": 0.5984125789631048,
        "extraversion": 0.5238196659549063,
        "agreeableness": 0.6362408386003894,
        "neuroticism": 0.49548212474567843
    },
    "Semigradsky": {
        "openness": 0.8021360570609605,
        "conscientiousness": 0.5989763031831772,
        "extraversion": 0.4819351148393486,
        "agreeableness": 0.6474950711652678,
        "neuroticism": 0.5125809206739111
    },
    "pkmiec": {
        "openness": 0.8188566957314793,
        "conscientiousness": 0.5872082116777231,
        "extraversion": 0.5005027776590937,
        "agreeableness": 0.6326544872277218,
        "neuroticism": 0.5232247081742796
    },
    "Nicolab": {
        "openness": 0.8242575583321536,
        "conscientiousness": 0.604272302808297,
        "extraversion": 0.4940218899716632,
        "agreeableness": 0.6710272982130703,
        "neuroticism": 0.5355454428285951
    },
    "twisty": {
        "openness": 0.8243177202320827,
        "conscientiousness": 0.5800586075350195,
        "extraversion": 0.4631560110455266,
        "agreeableness": 0.6054523973610868,
        "neuroticism": 0.4906940657540742
    },
    "ordinathorreur": {
        "openness": 0.8183521833850491,
        "conscientiousness": 0.5534104818459408,
        "extraversion": 0.4491137135645532,
        "agreeableness": 0.6044822286172311,
        "neuroticism": 0.5014842214946239
    },
    "th3fallen": {
        "openness": 0.8012716874654624,
        "conscientiousness": 0.5796387925337697,
        "extraversion": 0.4805908412320752,
        "agreeableness": 0.7199691063195521,
        "neuroticism": 0.44949015717485147
    },
    "sallomendo": {
        "openness": 0.7666750063742944,
        "conscientiousness": 0.5585776105233433,
        "extraversion": 0.4822080424473106,
        "agreeableness": 0.6440727264553838,
        "neuroticism": 0.4892023314653662
    },
    "worklez": {
        "openness": 0.778700225059183,
        "conscientiousness": 0.5392903254879307,
        "extraversion": 0.5136106446403652,
        "agreeableness": 0.6261020116824497,
        "neuroticism": 0.41485753795429203
    },
    "morenoh149": {
        "openness": 0.808203906049605,
        "conscientiousness": 0.589961763607087,
        "extraversion": 0.46228517397687896,
        "agreeableness": 0.6454581406986195,
        "neuroticism": 0.5019836546243212
    },
    "tomaash": {
        "openness": 0.821572206185219,
        "conscientiousness": 0.5958239186574887,
        "extraversion": 0.49726640833700586,
        "agreeableness": 0.6798663645638134,
        "neuroticism": 0.47818210831439767
    },
    "vijayrawatsan": {
        "openness": 0.8177362619712462,
        "conscientiousness": 0.5738568442525598,
        "extraversion": 0.45673577642987084,
        "agreeableness": 0.6266593855634753,
        "neuroticism": 0.4703826649648084
    },
    "cdeutsch": {
        "openness": 0.7953286164897381,
        "conscientiousness": 0.5599382222035826,
        "extraversion": 0.4590600934444403,
        "agreeableness": 0.5810387694448972,
        "neuroticism": 0.5113335825459393
    },
    "ntucker": {
        "openness": 0.8168430115793696,
        "conscientiousness": 0.5792091423145757,
        "extraversion": 0.5322085039174849,
        "agreeableness": 0.6735183613018145,
        "neuroticism": 0.5319513608314796
    },
    "ivome": {
        "openness": 0.7925439191523943,
        "conscientiousness": 0.5574676681094355,
        "extraversion": 0.46690369885809796,
        "agreeableness": 0.629660804490382,
        "neuroticism": 0.4618206452968769
    },
    "chrbala": {
        "openness": 0.8607169372124688,
        "conscientiousness": 0.5674385154050875,
        "extraversion": 0.5629593917133122,
        "agreeableness": 0.6820167683394961,
        "neuroticism": 0.5342025194131009
    },
    "ericdfields": {
        "openness": 0.8468057735665911,
        "conscientiousness": 0.5581367371079161,
        "extraversion": 0.526201971179346,
        "agreeableness": 0.6633163247951406,
        "neuroticism": 0.49149944136047635
    },
    "dsteinbach": {
        "openness": 0.8325612327904951,
        "conscientiousness": 0.5590384993013289,
        "extraversion": 0.4725836723405515,
        "agreeableness": 0.6082038590753788,
        "neuroticism": 0.4563166707462697
    },
    "colinmccann": {
        "openness": 0.8082122481750088,
        "conscientiousness": 0.5855800574766811,
        "extraversion": 0.4872541309539983,
        "agreeableness": 0.6599919931382926,
        "neuroticism": 0.4987015026124969
    },
    "aphillipo": {
        "openness": 0.8073517453308952,
        "conscientiousness": 0.5658603476056665,
        "extraversion": 0.4501915934070829,
        "agreeableness": 0.627903327068468,
        "neuroticism": 0.45430463925472586
    },
    "mbrookes": {
        "openness": 0.8025772163634066,
        "conscientiousness": 0.5792343259539164,
        "extraversion": 0.5084944496586777,
        "agreeableness": 0.6734646191642043,
        "neuroticism": 0.47339548281631616
    },
    "davidtinker": {
        "openness": 0.7643549673059036,
        "conscientiousness": 0.5842360644308464,
        "extraversion": 0.47297447322333874,
        "agreeableness": 0.6977502450240415,
        "neuroticism": 0.41668916998555305
    },
    "adrienharnay": {
        "openness": 0.782723322750374,
        "conscientiousness": 0.5870254669842772,
        "extraversion": 0.5335953048238383,
        "agreeableness": 0.688060250913781,
        "neuroticism": 0.42208715768301913
    },
    "mindcruzer": {
        "openness": 0.7806711504136205,
        "conscientiousness": 0.5432883151001857,
        "extraversion": 0.4804134218363225,
        "agreeableness": 0.6195697308471655,
        "neuroticism": 0.40132481114408514
    },
    "silvenon": {
        "openness": 0.8218080834780902,
        "conscientiousness": 0.5652747776228428,
        "extraversion": 0.4358834891614402,
        "agreeableness": 0.6528366682974167,
        "neuroticism": 0.4583430417248369
    },
    "achtan": {
        "openness": 0.7527779757392673,
        "conscientiousness": 0.5945260199187135,
        "extraversion": 0.573934102318618,
        "agreeableness": 0.7049688701002904,
        "neuroticism": 0.5203823546824309
    },
    "richardaday": {
        "openness": 0.8238442908558519,
        "conscientiousness": 0.5908097131146315,
        "extraversion": 0.4958198960051459,
        "agreeableness": 0.6409711614513717,
        "neuroticism": 0.4917715394089912
    },
    "idream3": {
        "openness": 0.7971547255303197,
        "conscientiousness": 0.5998308890029117,
        "extraversion": 0.4566137244021717,
        "agreeableness": 0.6226237225041193,
        "neuroticism": 0.5012756552471466
    },
    "dptoot": {
        "openness": 0.8265903170139702,
        "conscientiousness": 0.6061464615324743,
        "extraversion": 0.49344919424828204,
        "agreeableness": 0.637718256713018,
        "neuroticism": 0.5062458042533776
    },
    "Ezekiah": {
        "openness": 0.7882775300576526,
        "conscientiousness": 0.5828806440828943,
        "extraversion": 0.4916816292796915,
        "agreeableness": 0.6245739446794223,
        "neuroticism": 0.4540229511261617
    },
    "eriknyk": {
        "openness": 0.8240531516229683,
        "conscientiousness": 0.6048837156540785,
        "extraversion": 0.507445190834422,
        "agreeableness": 0.6467963662267538,
        "neuroticism": 0.4732505385164033
    },
    "jaraquistain": {
        "openness": 0.8413765200132708,
        "conscientiousness": 0.6054447035775035,
        "extraversion": 0.5325544158284842,
        "agreeableness": 0.6375940895273475,
        "neuroticism": 0.5140123072959378
    },
    "rodryquintero": {
        "openness": 0.8138519467210859,
        "conscientiousness": 0.5712204282328837,
        "extraversion": 0.489024155336816,
        "agreeableness": 0.6358957167588926,
        "neuroticism": 0.49608867994453365
    },
    "r-tock": {
        "openness": 0.8057173404836551,
        "conscientiousness": 0.590941748169681,
        "extraversion": 0.46812286300659545,
        "agreeableness": 0.6061983040556667,
        "neuroticism": 0.4450804490592034
    },
    "ghost": {
        "openness": 0.8390292700990895,
        "conscientiousness": 0.5674771062410637,
        "extraversion": 0.5427914605864961,
        "agreeableness": 0.6034763828473122,
        "neuroticism": 0.5017187173523879
    },
    "davidblurton": {
        "openness": 0.7866475123017258,
        "conscientiousness": 0.6312027974902981,
        "extraversion": 0.46665979909700717,
        "agreeableness": 0.6779054943074181,
        "neuroticism": 0.5662211809293267
    },
    "martinpesout": {
        "openness": 0.7935898098002702,
        "conscientiousness": 0.5607233343391584,
        "extraversion": 0.5187316282313862,
        "agreeableness": 0.6346079298447328,
        "neuroticism": 0.42242855970772253
    },
    "arnif": {
        "openness": 0.7571721843602577,
        "conscientiousness": 0.5586627255750984,
        "extraversion": 0.4126574482032547,
        "agreeableness": 0.6310270275486225,
        "neuroticism": 0.3662983354969602
    },
    "damon-kreft": {
        "openness": 0.8558794803982857,
        "conscientiousness": 0.582134498248977,
        "extraversion": 0.48867302656695094,
        "agreeableness": 0.6241102510151351,
        "neuroticism": 0.49384196530959956
    },
    "clayne11": {
        "openness": 0.817264360412358,
        "conscientiousness": 0.5764820623790213,
        "extraversion": 0.48470041184663026,
        "agreeableness": 0.5788331064191163,
        "neuroticism": 0.492912605332573
    },
    "0m15": {
        "openness": 0.8133849305455908,
        "conscientiousness": 0.5855774821166373,
        "extraversion": 0.5015765155220123,
        "agreeableness": 0.626855201023049,
        "neuroticism": 0.5019625674973143
    },
    "track0x1": {
        "openness": 0.827471753428288,
        "conscientiousness": 0.584742741918021,
        "extraversion": 0.45801343506173087,
        "agreeableness": 0.6215731996657543,
        "neuroticism": 0.5033371868704617
    },
    "ciaoben": {
        "openness": 0.8327014796874538,
        "conscientiousness": 0.6178737003647188,
        "extraversion": 0.4551913528123793,
        "agreeableness": 0.5932615237689005,
        "neuroticism": 0.5474290393557444
    },
    "aight8": {
        "openness": 0.7912788470464983,
        "conscientiousness": 0.5446907856675537,
        "extraversion": 0.4427948338738251,
        "agreeableness": 0.6258725064213796,
        "neuroticism": 0.4499972300433644
    },
    "NOlanguage1993": {
        "openness": 0.7720524045204211,
        "conscientiousness": 0.5777376567366473,
        "extraversion": 0.4834515673396828,
        "agreeableness": 0.6472868948281019,
        "neuroticism": 0.42099995147578484
    },
    "gCardinal": {
        "openness": 0.812467965931117,
        "conscientiousness": 0.5352280423925488,
        "extraversion": 0.42212466336159277,
        "agreeableness": 0.6375619479330946,
        "neuroticism": 0.3872619392088715
    },
    "charleskoehl": {
        "openness": 0.7793137993057021,
        "conscientiousness": 0.5882822155898395,
        "extraversion": 0.5065088097455909,
        "agreeableness": 0.6711982099563912,
        "neuroticism": 0.43490937563916243
    },
    "fxfilmxf": {
        "openness": 0.7950956173133811,
        "conscientiousness": 0.5870141304533711,
        "extraversion": 0.5029190861856666,
        "agreeableness": 0.6513353399464653,
        "neuroticism": 0.4109079057532514
    },
    "Jareechang": {
        "openness": 0.7927111119574519,
        "conscientiousness": 0.6634836595623332,
        "extraversion": 0.5453110100660808,
        "agreeableness": 0.7251625962645454,
        "neuroticism": 0.4876932768112596
    },
    "acomito": {
        "openness": 0.7935556835022504,
        "conscientiousness": 0.5826014447415715,
        "extraversion": 0.440099526406724,
        "agreeableness": 0.629106198028315,
        "neuroticism": 0.47540676518508673
    },
    "scottburch": {
        "openness": 0.8151171285563253,
        "conscientiousness": 0.6043435806414058,
        "extraversion": 0.48312056709338624,
        "agreeableness": 0.6566313983775889,
        "neuroticism": 0.512440691568121
    },
    "rkuykendall": {
        "openness": 0.838186695965014,
        "conscientiousness": 0.6380300853206134,
        "extraversion": 0.5089371479940645,
        "agreeableness": 0.6648169419264374,
        "neuroticism": 0.4745208824434686
    },
    "cgood92": {
        "openness": 0.8685047476220784,
        "conscientiousness": 0.6220045681616461,
        "extraversion": 0.5041882700324241,
        "agreeableness": 0.6190483933952691,
        "neuroticism": 0.5168481520198289
    },
    "prasanna1211": {
        "openness": 0.8189828164624025,
        "conscientiousness": 0.6185111068381861,
        "extraversion": 0.47554911032974595,
        "agreeableness": 0.6319817937974733,
        "neuroticism": 0.5134579504166739
    },
    "lennardschutter": {
        "openness": 0.8306976677222577,
        "conscientiousness": 0.632233609981267,
        "extraversion": 0.5114441511219382,
        "agreeableness": 0.6324400428831003,
        "neuroticism": 0.5483502899426226
    },
    "hak11": {
        "openness": 0.7687085784656246,
        "conscientiousness": 0.5953962615623624,
        "extraversion": 0.48323629458757067,
        "agreeableness": 0.6670850842684772,
        "neuroticism": 0.41313294584175264
    },
    "martinhbramwell": {
        "openness": 0.799619406954583,
        "conscientiousness": 0.5597507302938892,
        "extraversion": 0.4490475885237198,
        "agreeableness": 0.620112121407927,
        "neuroticism": 0.47036912600855224
    },
    "mathportillo": {
        "openness": 0.8311817553535404,
        "conscientiousness": 0.5657753828927953,
        "extraversion": 0.49290633570704967,
        "agreeableness": 0.6170413247418001,
        "neuroticism": 0.45334195238354225
    },
    "01binary": {
        "openness": 0.8146829214002624,
        "conscientiousness": 0.585156232583782,
        "extraversion": 0.4985621454761032,
        "agreeableness": 0.6165615890130471,
        "neuroticism": 0.5008425776881222
    },
    "cristianocca": {
        "openness": 0.8396546466581557,
        "conscientiousness": 0.6055793807303566,
        "extraversion": 0.48026447348155277,
        "agreeableness": 0.6125462888340694,
        "neuroticism": 0.5479124558696511
    },
    "brianfegan": {
        "openness": 0.8470602619696529,
        "conscientiousness": 0.570476524172947,
        "extraversion": 0.5097773650052184,
        "agreeableness": 0.5918162061960075,
        "neuroticism": 0.5138287729495441
    },
    "shalkam": {
        "openness": 0.8399094996081851,
        "conscientiousness": 0.5989696154746458,
        "extraversion": 0.5708783960729245,
        "agreeableness": 0.634157136227977,
        "neuroticism": 0.5588645729912621
    },
    "jganz": {
        "openness": 0.7899045862725358,
        "conscientiousness": 0.614466665631586,
        "extraversion": 0.44845027676325827,
        "agreeableness": 0.6137982107073074,
        "neuroticism": 0.5221092148601242
    },
    "brandondurham": {
        "openness": 0.7874594325307068,
        "conscientiousness": 0.5607723703448868,
        "extraversion": 0.42754873592162024,
        "agreeableness": 0.6675661719730757,
        "neuroticism": 0.46321504258798263
    },
    "leemachin": {
        "openness": 0.8194845929710974,
        "conscientiousness": 0.6253537826173241,
        "extraversion": 0.4399704913954747,
        "agreeableness": 0.6173212946509965,
        "neuroticism": 0.4822822210044122
    },
    "samuv": {
        "openness": 0.8048226223428282,
        "conscientiousness": 0.6868823307216412,
        "extraversion": 0.5072365471114834,
        "agreeableness": 0.7082605805756421,
        "neuroticism": 0.5237987307650696
    },
    "maccuaa": {
        "openness": 0.8292550122315984,
        "conscientiousness": 0.5955513105991974,
        "extraversion": 0.42769049252649416,
        "agreeableness": 0.6983881967230223,
        "neuroticism": 0.4693137760877927
    },
    "aliogaili": {
        "openness": 0.7869545780695945,
        "conscientiousness": 0.5360273610400778,
        "extraversion": 0.4323986631676434,
        "agreeableness": 0.5898748082695472,
        "neuroticism": 0.42962896743258483
    }
}