{
    "tobegit3hub": {
        "openness": 0.7921070937899268,
        "conscientiousness": 0.6385852240790819,
        "extraversion": 0.4763599266255586,
        "agreeableness": 0.6707746104828713,
        "neuroticism": 0.5185940746385542
    },
    "larrycai": {
        "openness": 0.7832828031055369,
        "conscientiousness": 0.6019019742655392,
        "extraversion": 0.4865715653369266,
        "agreeableness": 0.6423030499061413,
        "neuroticism": 0.49064913681066
    },
    "ozbillwang": {
        "openness": 0.7931808629009762,
        "conscientiousness": 0.6195601416432297,
        "extraversion": 0.5276406185887279,
        "agreeableness": 0.6225859794781177,
        "neuroticism": 0.524298026689848
    },
    "dlsniper": {
        "openness": 0.8026679091669536,
        "conscientiousness": 0.6470876449495777,
        "extraversion": 0.45372492634823575,
        "agreeableness": 0.6539060943542137,
        "neuroticism": 0.5221019471648002
    }
}