{
    "word_count": 776,
    "processed_language": "en",
    "personality": [
        {
            "trait_id": "big5_openness",
            "name": "Openness",
            "category": "personality",
            "percentile": 0.9740528220736164,
            "raw_score": 0.8107177580133419,
            "significant": true,
            "children": [
                {
                    "trait_id": "facet_adventurousness",
                    "name": "Adventurousness",
                    "category": "personality",
                    "percentile": 0.5823909696337783,
                    "raw_score": 0.5122158691905137,
                    "significant": true
                },
                {
                    "trait_id": "facet_artistic_interests",
                    "name": "Artistic interests",
                    "category": "personality",
                    "percentile": 0.5009082006489102,
                    "raw_score": 0.6654399901833421,
                    "significant": true
                },
                {
                    "trait_id": "facet_emotionality",
                    "name": "Emotionality",
                    "category": "personality",
                    "percentile": 0.10805058840475179,
                    "raw_score": 0.5977656204127291,
                    "significant": true
                },
                {
                    "trait_id": "facet_imagination",
                    "name": "Imagination",
                    "category": "personality",
                    "percentile": 0.654411004069753,
                    "raw_score": 0.7545906229494086,
                    "significant": true
                },
                {
                    "trait_id": "facet_intellect",
                    "name": "Intellect",
                    "category": "personality",
                    "percentile": 0.9853718771816953,
                    "raw_score": 0.7081533100745445,
                    "significant": true
                },
                {
                    "trait_id": "facet_liberalism",
                    "name": "Authority-challenging",
                    "category": "personality",
                    "percentile": 0.9204461969164961,
                    "raw_score": 0.5871493334293745,
                    "significant": true
                }
            ]
        },
        {
            "trait_id": "big5_conscientiousness",
            "name": "Conscientiousness",
            "category": "personality",
            "percentile": 0.13243731931067837,
            "raw_score": 0.5760490904736665,
            "significant": true,
            "children": [
                {
                    "trait_id": "facet_achievement_striving",
                    "name": "Achievement striving",
                    "category": "personality",
                    "percentile": 0.15869494700264758,
                    "raw_score": 0.6354626765307207,
                    "significant": true
                },
                {
                    "trait_id": "facet_cautiousness",
                    "name": "Cautiousness",
                    "category": "personality",
                    "percentile": 0.8282411803148231,
                    "raw_score": 0.5522684418548833,
                    "significant": true
                },
                {
                    "trait_id": "facet_dutifulness",
                    "name": "Dutifulness",
                    "category": "personality",
                    "percentile": 0.28103976603931724,
                    "raw_score": 0.6447024002456876,
                    "significant": true
                },
                {
                    "trait_id": "facet_orderliness",
                    "name": "Orderliness",
                    "category": "personality",
                    "percentile": 0.03669945139267011,
                    "raw_score": 0.4355117985800738,
                    "significant": true
                },
                {
                    "trait_id": "facet_self_discipline",
                    "name": "Self-discipline",
                    "category": "personality",
                    "percentile": 0.08768344308463039,
                    "raw_score": 0.5060987606947985,
                    "significant": true
                },
                {
                    "trait_id": "facet_self_efficacy",
                    "name": "Self-efficacy",
                    "category": "personality",
                    "percentile": 0.025062597675907072,
                    "raw_score": 0.6842089214570297,
                    "significant": true
                }
            ]
        },
        {
            "trait_id": "big5_extraversion",
            "name": "Extraversion",
            "category": "personality",
            "percentile": 0.03226512492926242,
            "raw_score": 0.46851952748594133,
            "significant": true,
            "children": [
                {
                    "trait_id": "facet_activity_level",
                    "name": "Activity level",
                    "category": "personality",
                    "percentile": 0.4464413667407844,
                    "raw_score": 0.5334890074136767,
                    "significant": true
                },
                {
                    "trait_id": "facet_assertiveness",
                    "name": "Assertiveness",
                    "category": "personality",
                    "percentile": 0.05357340273553035,
                    "raw_score": 0.5635169062395636,
                    "significant": true
                },
                {
                    "trait_id": "facet_cheerfulness",
                    "name": "Cheerfulness",
                    "category": "personality",
                    "percentile": 3.906399601305566e-05,
                    "raw_score": 0.4855773351125059,
                    "significant": true
                },
                {
                    "trait_id": "facet_excitement_seeking",
                    "name": "Excitement-seeking",
                    "category": "personality",
                    "percentile": 0.007002186427287949,
                    "raw_score": 0.49942086662468843,
                    "significant": true
                },
                {
                    "trait_id": "facet_friendliness",
                    "name": "Outgoing",
                    "category": "personality",
                    "percentile": 0.0003177717187295426,
                    "raw_score": 0.3891585502591928,
                    "significant": true
                },
                {
                    "trait_id": "facet_gregariousness",
                    "name": "Gregariousness",
                    "category": "personality",
                    "percentile": 7.333020863253825e-06,
                    "raw_score": 0.23054845415019368,
                    "significant": true
                }
            ]
        },
        {
            "trait_id": "big5_agreeableness",
            "name": "Agreeableness",
            "category": "personality",
            "percentile": 0.005105103806687439,
            "raw_score": 0.6400837699016955,
            "significant": true,
            "children": [
                {
                    "trait_id": "facet_altruism",
                    "name": "Altruism",
                    "category": "personality",
                    "percentile": 0.05303111753880607,
                    "raw_score": 0.6483938090970418,
                    "significant": true
                },
                {
                    "trait_id": "facet_cooperation",
                    "name": "Cooperation",
                    "category": "personality",
                    "percentile": 0.6947422648162689,
                    "raw_score": 0.6100755000548665,
                    "significant": true
                },
                {
                    "trait_id": "facet_modesty",
                    "name": "Modesty",
                    "category": "personality",
                    "percentile": 0.5844080715445799,
                    "raw_score": 0.45962468879263585,
                    "significant": true
                },
                {
                    "trait_id": "facet_morality",
                    "name": "Uncompromising",
                    "category": "personality",
                    "percentile": 0.5994231601667245,
                    "raw_score": 0.6376944236129067,
                    "significant": true
                },
                {
                    "trait_id": "facet_sympathy",
                    "name": "Sympathy",
                    "category": "personality",
                    "percentile": 0.4199182387706868,
                    "raw_score": 0.655761022743306,
                    "significant": true
                },
                {
                    "trait_id": "facet_trust",
                    "name": "Trust",
                    "category": "personality",
                    "percentile": 0.11057006795171564,
                    "raw_score": 0.5353969274828014,
                    "significant": true
                }
            ]
        },
        {
            "trait_id": "big5_neuroticism",
            "name": "Emotional range",
            "category": "personality",
            "percentile": 0.5765710277542427,
            "raw_score": 0.47825280984828705,
            "significant": true,
            "children": [
                {
                    "trait_id": "facet_anger",
                    "name": "Fiery",
                    "category": "personality",
                    "percentile": 0.867214497470849,
                    "raw_score": 0.5965982336707684,
                    "significant": true
                },
                {
                    "trait_id": "facet_anxiety",
                    "name": "Prone to worry",
                    "category": "personality",
                    "percentile": 0.7171477831831821,
                    "raw_score": 0.6332835467252088,
                    "significant": true
                },
                {
                    "trait_id": "facet_depression",
                    "name": "Melancholy",
                    "category": "personality",
                    "percentile": 0.9922681987825068,
                    "raw_score": 0.601801581010565,
                    "significant": true
                },
                {
                    "trait_id": "facet_immoderation",
                    "name": "Immoderation",
                    "category": "personality",
                    "percentile": 0.2679332231576044,
                    "raw_score": 0.4767983611065625,
                    "significant": true
                },
                {
                    "trait_id": "facet_self_consciousness",
                    "name": "Self-consciousness",
                    "category": "personality",
                    "percentile": 0.9942024656840938,
                    "raw_score": 0.6795382755423249,
                    "significant": true
                },
                {
                    "trait_id": "facet_vulnerability",
                    "name": "Susceptible to stress",
                    "category": "personality",
                    "percentile": 0.9706916817689,
                    "raw_score": 0.5881034889819966,
                    "significant": true
                }
            ]
        }
    ],
    "needs": [
        {
            "trait_id": "need_challenge",
            "name": "Challenge",
            "category": "needs",
            "percentile": 0.1756787390133887,
            "raw_score": 0.6899873341843298,
            "significant": true
        },
        {
            "trait_id": "need_closeness",
            "name": "Closeness",
            "category": "needs",
            "percentile": 0.001335960260689606,
            "raw_score": 0.6600611847182724,
            "significant": true
        },
        {
            "trait_id": "need_curiosity",
            "name": "Curiosity",
            "category": "needs",
            "percentile": 0.9283659285769348,
            "raw_score": 0.85517413658596,
            "significant": true
        },
        {
            "trait_id": "need_excitement",
            "name": "Excitement",
            "category": "needs",
            "percentile": 0.0386637760365261,
            "raw_score": 0.5448896161263921,
            "significant": true
        },
        {
            "trait_id": "need_harmony",
            "name": "Harmony",
            "category": "needs",
            "percentile": 0.008677506545249014,
            "raw_score": 0.7271070636591351,
            "significant": true
        },
        {
            "trait_id": "need_ideal",
            "name": "Ideal",
            "category": "needs",
            "percentile": 0.41911687244665896,
            "raw_score": 0.681352749358969,
            "significant": true
        },
        {
            "trait_id": "need_liberty",
            "name": "Liberty",
            "category": "needs",
            "percentile": 0.3489547413881462,
            "raw_score": 0.721971004480971,
            "significant": true
        },
        {
            "trait_id": "need_love",
            "name": "Love",
            "category": "needs",
            "percentile": 0.0004940157556954095,
            "raw_score": 0.6084251010831744,
            "significant": true
        },
        {
            "trait_id": "need_practicality",
            "name": "Practicality",
            "category": "needs",
            "percentile": 0.7181066875656065,
            "raw_score": 0.7402446122877704,
            "significant": true
        },
        {
            "trait_id": "need_self_expression",
            "name": "Self-expression",
            "category": "needs",
            "percentile": 0.3643033294157933,
            "raw_score": 0.6630699254974591,
            "significant": true
        },
        {
            "trait_id": "need_stability",
            "name": "Stability",
            "category": "needs",
            "percentile": 0.017356945581909367,
            "raw_score": 0.6671983266413499,
            "significant": true
        },
        {
            "trait_id": "need_structure",
            "name": "Structure",
            "category": "needs",
            "percentile": 0.12012592364475821,
            "raw_score": 0.66425713921576,
            "significant": true
        }
    ],
    "values": [
        {
            "trait_id": "value_conservation",
            "name": "Conservation",
            "category": "values",
            "percentile": 1.3642964463156382e-05,
            "raw_score": 0.4764643681317935,
            "significant": true
        },
        {
            "trait_id": "value_openness_to_change",
            "name": "Openness to change",
            "category": "values",
            "percentile": 0.23387603290648695,
            "raw_score": 0.7562672356437257,
            "significant": true
        },
        {
            "trait_id": "value_hedonism",
            "name": "Hedonism",
            "category": "values",
            "percentile": 0.02301570181791246,
            "raw_score": 0.6107048211302912,
            "significant": true
        },
        {
            "trait_id": "value_self_enhancement",
            "name": "Self-enhancement",
            "category": "values",
            "percentile": 0.03091119136997661,
            "raw_score": 0.6243962784514747,
            "significant": true
        },
        {
            "trait_id": "value_self_transcendence",
            "name": "Self-transcendence",
            "category": "values",
            "percentile": 0.18471513003802698,
            "raw_score": 0.8183398666199446,
            "significant": true
        }
    ],
    "consumption_preferences": [
        {
            "consumption_preference_category_id": "consumption_preferences_shopping",
            "name": "Purchasing Preferences",
            "consumption_preferences": [
                {
                    "consumption_preference_id": "consumption_preferences_automobile_ownership_cost",
                    "name": "Likely to be sensitive to ownership cost when buying automobiles",
                    "score": 1.0
                },
                {
                    "consumption_preference_id": "consumption_preferences_automobile_safety",
                    "name": "Likely to prefer safety when buying automobiles",
                    "score": 0.0
                },
                {
                    "consumption_preference_id": "consumption_preferences_clothes_quality",
                    "name": "Likely to prefer quality when buying clothes",
                    "score": 1.0
                },
                {
                    "consumption_preference_id": "consumption_preferences_clothes_style",
                    "name": "Likely to prefer style when buying clothes",
                    "score": 0.0
                },
                {
                    "consumption_preference_id": "consumption_preferences_clothes_comfort",
                    "name": "Likely to prefer comfort when buying clothes",
                    "score": 1.0
                },
                {
                    "consumption_preference_id": "consumption_preferences_influence_brand_name",
                    "name": "Likely to be influenced by brand name when making product purchases",
                    "score": 0.0
                },
                {
                    "consumption_preference_id": "consumption_preferences_influence_utility",
                    "name": "Likely to be influenced by product utility when making product purchases",
                    "score": 1.0
                },
                {
                    "consumption_preference_id": "consumption_preferences_influence_online_ads",
                    "name": "Likely to be influenced by online ads when making product purchases",
                    "score": 0.0
                },
                {
                    "consumption_preference_id": "consumption_preferences_influence_social_media",
                    "name": "Likely to be influenced by social media when making product purchases",
                    "score": 0.0
                },
                {
                    "consumption_preference_id": "consumption_preferences_influence_family_members",
                    "name": "Likely to be influenced by family when making product purchases",
                    "score": 0.0
                },
                {
                    "consumption_preference_id": "consumption_preferences_spur_of_moment",
                    "name": "Likely to indulge in spur of the moment purchases",
                    "score": 0.0
                },
                {
                    "consumption_preference_id": "consumption_preferences_credit_card_payment",
                    "name": "Likely to prefer using credit cards for shopping",
                    "score": 1.0
                }
            ]
        },
        {
            "consumption_preference_category_id": "consumption_preferences_health_and_activity",
            "name": "Health & Activity Preferences",
            "consumption_preferences": [
                {
                    "consumption_preference_id": "consumption_preferences_eat_out",
                    "name": "Likely to eat out frequently",
                    "score": 0.0
                },
                {
                    "consumption_preference_id": "consumption_preferences_gym_membership",
                    "name": "Likely to have a gym membership",
                    "score": 0.0
                },
                {
                    "consumption_preference_id": "consumption_preferences_outdoor",
                    "name": "Likely to like outdoor activities",
                    "score": 0.5
                }
            ]
        },
        {
            "consumption_preference_category_id": "consumption_preferences_environmental_concern",
            "name": "Environmental Concern Preferences",
            "consumption_preferences": [
                {
                    "consumption_preference_id": "consumption_preferences_concerned_environment",
                    "name": "Likely to be concerned about the environment",
                    "score": 1.0
                }
            ]
        },
        {
            "consumption_preference_category_id": "consumption_preferences_entrepreneurship",
            "name": "Entrepreneurship Preferences",
            "consumption_preferences": [
                {
                    "consumption_preference_id": "consumption_preferences_start_business",
                    "name": "Likely to consider starting a business in next few years",
                    "score": 0.5
                }
            ]
        },
        {
            "consumption_preference_category_id": "consumption_preferences_movie",
            "name": "Movie Preferences",
            "consumption_preferences": [
                {
                    "consumption_preference_id": "consumption_preferences_movie_romance",
                    "name": "Likely to like romance movies",
                    "score": 0.0
                },
                {
                    "consumption_preference_id": "consumption_preferences_movie_adventure",
                    "name": "Likely to like adventure movies",
                    "score": 1.0
                },
                {
                    "consumption_preference_id": "consumption_preferences_movie_horror",
                    "name": "Likely to like horror movies",
                    "score": 0.0
                },
                {
                    "consumption_preference_id": "consumption_preferences_movie_musical",
                    "name": "Likely to like musical movies",
                    "score": 0.0
                },
                {
                    "consumption_preference_id": "consumption_preferences_movie_historical",
                    "name": "Likely to like historical movies",
                    "score": 1.0
                },
                {
                    "consumption_preference_id": "consumption_preferences_movie_science_fiction",
                    "name": "Likely to like science-fiction movies",
                    "score": 1.0
                },
                {
                    "consumption_preference_id": "consumption_preferences_movie_war",
                    "name": "Likely to like war movies",
                    "score": 0.0
                },
                {
                    "consumption_preference_id": "consumption_preferences_movie_drama",
                    "name": "Likely to like drama movies",
                    "score": 0.0
                },
                {
                    "consumption_preference_id": "consumption_preferences_movie_action",
                    "name": "Likely to like action movies",
                    "score": 1.0
                },
                {
                    "consumption_preference_id": "consumption_preferences_movie_documentary",
                    "name": "Likely to like documentary movies",
                    "score": 1.0
                }
            ]
        },
        {
            "consumption_preference_category_id": "consumption_preferences_music",
            "name": "Music Preferences",
            "consumption_preferences": [
                {
                    "consumption_preference_id": "consumption_preferences_music_rap",
                    "name": "Likely to like rap music",
                    "score": 0.5
                },
                {
                    "consumption_preference_id": "consumption_preferences_music_country",
                    "name": "Likely to like country music",
                    "score": 0.0
                },
                {
                    "consumption_preference_id": "consumption_preferences_music_r_b",
                    "name": "Likely to like R&B music",
                    "score": 0.5
                },
                {
                    "consumption_preference_id": "consumption_preferences_music_hip_hop",
                    "name": "Likely to like hip hop music",
                    "score": 0.0
                },
                {
                    "consumption_preference_id": "consumption_preferences_music_live_event",
                    "name": "Likely to attend live musical events",
                    "score": 0.0
                },
                {
                    "consumption_preference_id": "consumption_preferences_music_playing",
                    "name": "Likely to have experience playing music",
                    "score": 1.0
                },
                {
                    "consumption_preference_id": "consumption_preferences_music_latin",
                    "name": "Likely to like Latin music",
                    "score": 1.0
                },
                {
                    "consumption_preference_id": "consumption_preferences_music_rock",
                    "name": "Likely to like rock music",
                    "score": 1.0
                },
                {
                    "consumption_preference_id": "consumption_preferences_music_classical",
                    "name": "Likely to like classical music",
                    "score": 1.0
                }
            ]
        },
        {
            "consumption_preference_category_id": "consumption_preferences_reading",
            "name": "Reading Preferences",
            "consumption_preferences": [
                {
                    "consumption_preference_id": "consumption_preferences_read_frequency",
                    "name": "Likely to read often",
                    "score": 1.0
                },
                {
                    "consumption_preference_id": "consumption_preferences_books_entertainment_magazines",
                    "name": "Likely to read entertainment magazines",
                    "score": 0.0
                },
                {
                    "consumption_preference_id": "consumption_preferences_books_non_fiction",
                    "name": "Likely to read non-fiction books",
                    "score": 1.0
                },
                {
                    "consumption_preference_id": "consumption_preferences_books_financial_investing",
                    "name": "Likely to read financial investment books",
                    "score": 0.0
                },
                {
                    "consumption_preference_id": "consumption_preferences_books_autobiographies",
                    "name": "Likely to read autobiographical books",
                    "score": 0.0
                }
            ]
        },
        {
            "consumption_preference_category_id": "consumption_preferences_volunteering",
            "name": "Volunteering Preferences",
            "consumption_preferences": [
                {
                    "consumption_preference_id": "consumption_preferences_volunteer",
                    "name": "Likely to volunteer for social causes",
                    "score": 0.0
                }
            ]
        }
    ],
    "warnings": []
}